__init__.py
anomalies.py
desolate.py
kaplan_meier.py
preprocessing.py
desolate-0.0.3.dist-info/LICENSE
desolate-0.0.3.dist-info/METADATA
desolate-0.0.3.dist-info/WHEEL
desolate-0.0.3.dist-info/top_level.txt
desolate-0.0.3.dist-info/RECORD
