Metadata-Version: 2.2
Name: desolate
Version: 0.0.3
Summary: Detecting Anomalies with Censors
Requires-Python: >=3.12
License-File: LICENSE
Requires-Dist: numpy>=2.2.2
